elementary_hpo/__init__.py
elementary_hpo/core.py
elementary_hpo/utils.py
elementary_hpo/visualization.py
elementary_hpo-0.2.0.dist-info/METADATA
elementary_hpo-0.2.0.dist-info/WHEEL
elementary_hpo-0.2.0.dist-info/licenses/LICENSE
elementary_hpo-0.2.0.dist-info/RECORD
