Metadata-Version: 2.4
Name: elementary-hpo
Version: 0.2.0
Summary: A lightweight hyperparameter optimization tool using Sobol sequences.
License-Expression: Apache-2.0
License-File: LICENSE
Author: BetikuOluwatobi
Author-email: betikuoluwatobi7@gmail.com
Requires-Python: >=3.11
Classifier: Programming Language :: Python :: 3
Classifier: License :: OSI Approved :: Apache Software License
Classifier: Operating System :: OS Independent
Classifier: Topic :: Scientific/Engineering :: Artificial Intelligence
Requires-Dist: matplotlib
Requires-Dist: numpy
Requires-Dist: pandas
Requires-Dist: pytest (>=9.0.2,<10.0.0)
Requires-Dist: scikit-learn
Requires-Dist: scipy (>=1.7.0)
Requires-Dist: seaborn
Project-URL: Bug Tracker, https://github.com/BetikuOluwatobi/elementary-hpo/issues
Project-URL: Documentation, https://medium.com/@betikuoluwatobi7/quasi-random-search-a-smarter-way-to-tune-hyperparameters-in-python-2650fe69d106
Project-URL: Homepage, https://github.com/BetikuOluwatobi/elementary-hpo
